rlabs_mini_api/__init__.py
rlabs_mini_api/config.py
rlabs_mini_api/directory.py
rlabs_mini_api/error.py
rlabs_mini_api/logger.py
rlabs_mini_api/manual_test_run.py
rlabs_mini_api/py.typed
rlabs_mini_api/request.py
rlabs_mini_api/response.py
rlabs_mini_api-1.7.1.dist-info/METADATA
rlabs_mini_api-1.7.1.dist-info/WHEEL
rlabs_mini_api-1.7.1.dist-info/entry_points.txt
rlabs_mini_api-1.7.1.dist-info/RECORD
